how/__init__.py
how/__main__.py
how/formatting.py
how/how.py
how/infer.py
how/core/__init__.py
how/core/chains.py
how/core/config.py
how/core/llm.py
how/core/parser.py
how/core/prompts.py
how/core/providers.py
how/core/schema.py
how/core/template.py
how_cli-0.2.0.dist-info/LICENSE
how_cli-0.2.0.dist-info/METADATA
how_cli-0.2.0.dist-info/WHEEL
how_cli-0.2.0.dist-info/entry_points.txt
how_cli-0.2.0.dist-info/top_level.txt
how_cli-0.2.0.dist-info/RECORD
