Metadata-Version: 2.1
Name: how-cli
Version: 0.2.0
Summary: An AI-based CLI assistant to help you with command line & shell.
Home-page: https://github.com/FireHead90544/how-cli
Author: Rudransh Joshi (FireHead90544)
Author-email: rudranshjoshi1806@gmail.com
License: MIT
Project-URL: Issue Tracker, https://github.com/FireHead90544/how-cli/issues
Platform: any
License-File: LICENSE
Requires-Dist: typer
Requires-Dist: langchain
Requires-Dist: langchain-google-genai
Requires-Dist: langchain-google-vertexai
Requires-Dist: langchain-groq
Requires-Dist: langchain-openai
Requires-Dist: langchain-anthropic
